chesslib.cpython-36m-x86_64-linux-gnu.so
chesslib-1.0.340699405.dist-info/top_level.txt
chesslib-1.0.340699405.dist-info/WHEEL
chesslib-1.0.340699405.dist-info/METADATA
chesslib-1.0.340699405.dist-info/RECORD
chesslib-1.0.340699405.dist-info/LICENSE.md
