Metadata-Version: 2.1
Name: chesslib
Version: 1.0.340699405
Summary: Python3 library for efficient chess draw-gen functions
Home-page: https://github.com/Bonifatius94/ChessLib.Py
Author: Marco Tröster
Author-email: marco@troester-gmbh.de
License: UNKNOWN
Platform: UNKNOWN
Requires-Python: >=3.0.0
License-File: LICENSE.md
Requires-Dist: numpy
